darwin_fiftyone/__init__.py
darwin_fiftyone/darwin.py
darwin_fiftyone-2.1.2.dist-info/licenses/LICENSE
darwin_fiftyone-2.1.2.dist-info/METADATA
darwin_fiftyone-2.1.2.dist-info/WHEEL
darwin_fiftyone-2.1.2.dist-info/top_level.txt
darwin_fiftyone-2.1.2.dist-info/RECORD
