Metadata-Version: 2.4
Name: darwin-fiftyone
Version: 2.1.2
Summary: Integration between V7 Darwin and Voxel51
Home-page: https://github.com/v7labs/darwin_fiftyone
Author: Simon Edwardsson & Mark Cox-Smith
License-File: LICENSE
Requires-Dist: fiftyone>=0.22.0
Requires-Dist: darwin-py>=1.0.8
Requires-Dist: pycocotools>=2.0.6
Requires-Dist: numpy>=1.21.0
Requires-Dist: pandas>=1.3.0
Requires-Dist: Pillow>=9.0.0
Requires-Dist: opencv-python>=4.5.0
Requires-Dist: scikit-image>=0.19.0
Requires-Dist: tqdm>=4.65.0
Requires-Dist: requests>=2.28.0
Requires-Dist: python-dotenv>=0.19.0
Dynamic: author
Dynamic: description
Dynamic: description-content-type
Dynamic: home-page
Dynamic: license-file
Dynamic: requires-dist
Dynamic: summary
